{
  "last_updated": "2026-02-19T16:07:32",
  "data": [
    {
      "location": "Kurla, Mumbai - MPCB",
      "date": "2026-02-19",
      "time": "15:00:00",
      "PM2.5": 56,
      "PM10": 76,
      "NO": "NA",
      "NO2": 8,
      "NOx": "NA",
      "NH3": 2,
      "SO2": 37,
      "CO": 18,
      "Ozone": 28,
      "predominant": "PM10",
      "AQI": 76
    },
    {
      "location": "Chhatrapati Shivaji Intl. Airport (T2), Mumbai - MPCB",
      "date": "2026-02-19",
      "time": "15:00:00",
      "PM2.5": 51,
      "PM10": 62,
      "NO": "NA",
      "NO2": 2,
      "NOx": "NA",
      "NH3": "NA",
      "SO2": 22,
      "CO": "NA",
      "Ozone": "NA",
      "predominant": "PM10",
      "AQI": 62
    },
    {
      "location": "Vile Parle West, Mumbai - MPCB",
      "date": "2026-02-19",
      "time": "15:00:00",
      "PM2.5": "NA",
      "PM10": "NA",
      "NO": "NA",
      "NO2": "NA",
      "NOx": "NA",
      "NH3": "NA",
      "SO2": "NA",
      "CO": 21,
      "Ozone": "NA",
      "predominant": "NA",
      "AQI": "NA"
    },
    {
      "location": "Borivali East, Mumbai - MPCB",
      "date": "2026-02-19",
      "time": "15:00:00",
      "PM2.5": 21,
      "PM10": 31,
      "NO": "NA",
      "NO2": "NA",
      "NOx": "NA",
      "NH3": 5,
      "SO2": 17,
      "CO": 16,
      "Ozone": "NA",
      "predominant": "PM10",
      "AQI": 31
    },
    {
      "location": "Worli, Mumbai -MPCB",
      "date": "2026-02-19",
      "time": "15:00:00",
      "PM2.5": 62,
      "PM10": 97,
      "NO": "NA",
      "NO2": 35,
      "NOx": "NA",
      "NH3": 2,
      "SO2": "NA",
      "CO": 9,
      "Ozone": 158,
      "predominant": "OZONE",
      "AQI": 158
    },
    {
      "location": "Colaba, Mumbai - MPCB",
      "date": "2026-02-19",
      "time": "15:00:00",
      "PM2.5": 21,
      "PM10": 26,
      "NO": "NA",
      "NO2": "NA",
      "NOx": "NA",
      "NH3": "NA",
      "SO2": "NA",
      "CO": 60,
      "Ozone": 11,
      "predominant": "CO",
      "AQI": 60
    },
    {
      "location": "Mazgaon, Mumbai - IITM",
      "date": "2026-02-19",
      "time": "15:00:00",
      "PM2.5": 30,
      "PM10": 39,
      "NO": "NA",
      "NO2": 61,
      "NOx": "NA",
      "NH3": 10,
      "SO2": 20,
      "CO": 47,
      "Ozone": 52,
      "predominant": "NO2",
      "AQI": 61
    },
    {
      "location": "Bandra Kurla Complex, Mumbai - IITM",
      "date": "2026-02-19",
      "time": "15:00:00",
      "PM2.5": 49,
      "PM10": 63,
      "NO": "NA",
      "NO2": 52,
      "NOx": "NA",
      "NH3": "NA",
      "SO2": 2,
      "CO": 24,
      "Ozone": 14,
      "predominant": "PM10",
      "AQI": 63
    },
    {
      "location": "Borivali East, Mumbai - IITM",
      "date": "2026-02-19",
      "time": "15:00:00",
      "PM2.5": 43,
      "PM10": 68,
      "NO": "NA",
      "NO2": 29,
      "NOx": "NA",
      "NH3": 9,
      "SO2": "NA",
      "CO": 66,
      "Ozone": 40,
      "predominant": "PM10",
      "AQI": 68
    },
    {
      "location": "Malad West, Mumbai - IITM",
      "date": "2026-02-19",
      "time": "15:00:00",
      "PM2.5": 36,
      "PM10": 70,
      "NO": "NA",
      "NO2": 14,
      "NOx": "NA",
      "NH3": 23,
      "SO2": 11,
      "CO": 17,
      "Ozone": 72,
      "predominant": "OZONE",
      "AQI": 72
    },
    {
      "location": "Navy Nagar-Colaba, Mumbai - IITM",
      "date": "2026-02-19",
      "time": "15:00:00",
      "PM2.5": 43,
      "PM10": 55,
      "NO": "NA",
      "NO2": 38,
      "NOx": "NA",
      "NH3": 9,
      "SO2": 4,
      "CO": 28,
      "Ozone": 65,
      "predominant": "OZONE",
      "AQI": 65
    },
    {
      "location": "Chakala-Andheri East, Mumbai - IITM",
      "date": "2026-02-19",
      "time": "15:00:00",
      "PM2.5": 46,
      "PM10": 75,
      "NO": "NA",
      "NO2": 82,
      "NOx": "NA",
      "NH3": 16,
      "SO2": "NA",
      "CO": 10,
      "Ozone": 45,
      "predominant": "NO2",
      "AQI": 82
    },
    {
      "location": "Khindipada-Bhandup West, Mumbai - IITM",
      "date": "2026-02-19",
      "time": "15:00:00",
      "PM2.5": "NA",
      "PM10": 55,
      "NO": "NA",
      "NO2": 22,
      "NOx": "NA",
      "NH3": 5,
      "SO2": 7,
      "CO": 17,
      "Ozone": 61,
      "predominant": "OZONE",
      "AQI": 61
    },
    {
      "location": "Kandivali East, Mumbai - MPCB",
      "date": "2026-02-19",
      "time": "15:00:00",
      "PM2.5": 12,
      "PM10": 67,
      "NO": "NA",
      "NO2": 30,
      "NOx": "NA",
      "NH3": 3,
      "SO2": 25,
      "CO": 20,
      "Ozone": 18,
      "predominant": "PM10",
      "AQI": 67
    },
    {
      "location": "Siddharth Nagar-Worli, Mumbai - IITM",
      "date": "2026-02-19",
      "time": "15:00:00",
      "PM2.5": 23,
      "PM10": 42,
      "NO": "NA",
      "NO2": 52,
      "NOx": "NA",
      "NH3": 7,
      "SO2": "NA",
      "CO": 33,
      "Ozone": 52,
      "predominant": "NO2",
      "AQI": 52
    },
    {
      "location": "Bandra Kurla Complex, Mumbai - MPCB",
      "date": "2026-02-19",
      "time": "15:00:00",
      "PM2.5": 45,
      "PM10": 87,
      "NO": "NA",
      "NO2": 42,
      "NOx": "NA",
      "NH3": 10,
      "SO2": 7,
      "CO": 11,
      "Ozone": 36,
      "predominant": "PM10",
      "AQI": 87
    },
    {
      "location": "Chembur, Mumbai - MPCB",
      "date": "2026-02-19",
      "time": "15:00:00",
      "PM2.5": 33,
      "PM10": 54,
      "NO": "NA",
      "NO2": 41,
      "NOx": "NA",
      "NH3": 11,
      "SO2": 8,
      "CO": 18,
      "Ozone": 28,
      "predominant": "PM10",
      "AQI": 54
    },
    {
      "location": "Kherwadi_Bandra East, Mumbai - MPCB",
      "date": "2026-02-19",
      "time": "15:00:00",
      "PM2.5": 35,
      "PM10": 60,
      "NO": "NA",
      "NO2": 24,
      "NOx": "NA",
      "NH3": 10,
      "SO2": 3,
      "CO": 14,
      "Ozone": 30,
      "predominant": "PM10",
      "AQI": 60
    },
    {
      "location": "Byculla, Mumbai - BMC",
      "date": "2026-02-19",
      "time": "15:00:00",
      "PM2.5": 11,
      "PM10": 37,
      "NO": "NA",
      "NO2": 42,
      "NOx": "NA",
      "NH3": 8,
      "SO2": 2,
      "CO": 50,
      "Ozone": 18,
      "predominant": "CO",
      "AQI": 50
    },
    {
      "location": "Shivaji Nagar, Mumbai - BMC",
      "date": "2026-02-19",
      "time": "15:00:00",
      "PM2.5": 31,
      "PM10": 99,
      "NO": "NA",
      "NO2": 13,
      "NOx": "NA",
      "NH3": 4,
      "SO2": 7,
      "CO": 16,
      "Ozone": 14,
      "predominant": "PM10",
      "AQI": 99
    }
  ]
}