{
  "last_updated": "2025-04-20T10:48:15Z",
  "data": [
    {
      "location": "Kurla, Mumbai - MPCB",
      "date": "2025-04-20",
      "time": "15:00:00",
      "PM2.5": "NA",
      "PM10": 98,
      "NO": "NA",
      "NO2": 4,
      "NOx": "NA",
      "NH3": 1,
      "SO2": "NA",
      "CO": 5,
      "Ozone": 28,
      "predominant": "PM10",
      "AQI": 98
    },
    {
      "location": "Chhatrapati Shivaji Intl. Airport (T2), Mumbai - MPCB",
      "date": "2025-04-20",
      "time": "15:00:00",
      "PM2.5": 42,
      "PM10": 75,
      "NO": "NA",
      "NO2": 26,
      "NOx": "NA",
      "NH3": 1,
      "SO2": 21,
      "CO": 21,
      "Ozone": 7,
      "predominant": "PM10",
      "AQI": 75
    },
    {
      "location": "Powai, Mumbai - MPCB",
      "date": "2025-04-20",
      "time": "15:00:00",
      "PM2.5": 23,
      "PM10": 70,
      "NO": "NA",
      "NO2": 7,
      "NOx": "NA",
      "NH3": 2,
      "SO2": 26,
      "CO": 15,
      "Ozone": 9,
      "predominant": "PM10",
      "AQI": 70
    },
    {
      "location": "Colaba, Mumbai - MPCB",
      "date": "2025-04-20",
      "time": "15:00:00",
      "PM2.5": "NA",
      "PM10": 52,
      "NO": "NA",
      "NO2": 26,
      "NOx": "NA",
      "NH3": 3,
      "SO2": "NA",
      "CO": 26,
      "Ozone": 11,
      "predominant": "PM10",
      "AQI": 52
    },
    {
      "location": "Mazgaon, Mumbai - IITM",
      "date": "2025-04-20",
      "time": "15:00:00",
      "PM2.5": 27,
      "PM10": 58,
      "NO": "NA",
      "NO2": 51,
      "NOx": "NA",
      "NH3": 8,
      "SO2": 8,
      "CO": 38,
      "Ozone": 34,
      "predominant": "PM10",
      "AQI": 58
    },
    {
      "location": "Bandra Kurla Complex, Mumbai - IITM",
      "date": "2025-04-20",
      "time": "15:00:00",
      "PM2.5": 35,
      "PM10": 79,
      "NO": "NA",
      "NO2": 32,
      "NOx": "NA",
      "NH3": 3,
      "SO2": 3,
      "CO": 47,
      "Ozone": 14,
      "predominant": "PM10",
      "AQI": 79
    },
    {
      "location": "Borivali East, Mumbai - IITM",
      "date": "2025-04-20",
      "time": "15:00:00",
      "PM2.5": 38,
      "PM10": 58,
      "NO": "NA",
      "NO2": 41,
      "NOx": "NA",
      "NH3": 5,
      "SO2": "NA",
      "CO": 23,
      "Ozone": 30,
      "predominant": "PM10",
      "AQI": 58
    },
    {
      "location": "Malad West, Mumbai - IITM",
      "date": "2025-04-20",
      "time": "15:00:00",
      "PM2.5": 15,
      "PM10": 55,
      "NO": "NA",
      "NO2": 37,
      "NOx": "NA",
      "NH3": 5,
      "SO2": 7,
      "CO": 32,
      "Ozone": 34,
      "predominant": "PM10",
      "AQI": 55
    },
    {
      "location": "Navy Nagar-Colaba, Mumbai - IITM",
      "date": "2025-04-20",
      "time": "15:00:00",
      "PM2.5": 23,
      "PM10": 68,
      "NO": "NA",
      "NO2": 50,
      "NOx": "NA",
      "NH3": 3,
      "SO2": 18,
      "CO": 25,
      "Ozone": 36,
      "predominant": "PM10",
      "AQI": 68
    },
    {
      "location": "Chakala-Andheri East, Mumbai - IITM",
      "date": "2025-04-20",
      "time": "15:00:00",
      "PM2.5": "NA",
      "PM10": "NA",
      "NO": "NA",
      "NO2": "NA",
      "NOx": "NA",
      "NH3": "NA",
      "SO2": "NA",
      "CO": "NA",
      "Ozone": "NA",
      "predominant": "NA",
      "AQI": "NA"
    },
    {
      "location": "Khindipada-Bhandup West, Mumbai - IITM",
      "date": "2025-04-20",
      "time": "15:00:00",
      "PM2.5": 35,
      "PM10": 56,
      "NO": "NA",
      "NO2": 20,
      "NOx": "NA",
      "NH3": 2,
      "SO2": 14,
      "CO": 54,
      "Ozone": 50,
      "predominant": "PM10",
      "AQI": 56
    },
    {
      "location": "Kandivali East, Mumbai - MPCB",
      "date": "2025-04-20",
      "time": "15:00:00",
      "PM2.5": 78,
      "PM10": 99,
      "NO": "NA",
      "NO2": 1,
      "NOx": "NA",
      "NH3": 3,
      "SO2": "NA",
      "CO": "NA",
      "Ozone": "NA",
      "predominant": "PM10",
      "AQI": 99
    },
    {
      "location": "Siddharth Nagar-Worli, Mumbai - IITM",
      "date": "2025-04-20",
      "time": "15:00:00",
      "PM2.5": 27,
      "PM10": 62,
      "NO": "NA",
      "NO2": 21,
      "NOx": "NA",
      "NH3": 2,
      "SO2": "NA",
      "CO": 46,
      "Ozone": 46,
      "predominant": "PM10",
      "AQI": 62
    },
    {
      "location": "Bandra Kurla Complex, Mumbai - MPCB",
      "date": "2025-04-20",
      "time": "15:00:00",
      "PM2.5": 63,
      "PM10": 91,
      "NO": "NA",
      "NO2": 29,
      "NOx": "NA",
      "NH3": 7,
      "SO2": 2,
      "CO": 17,
      "Ozone": 53,
      "predominant": "PM10",
      "AQI": 91
    },
    {
      "location": "Chembur, Mumbai - MPCB",
      "date": "2025-04-20",
      "time": "15:00:00",
      "PM2.5": "NA",
      "PM10": "NA",
      "NO": "NA",
      "NO2": "NA",
      "NOx": "NA",
      "NH3": "NA",
      "SO2": "NA",
      "CO": 24,
      "Ozone": 43,
      "predominant": "NA",
      "AQI": "NA"
    },
    {
      "location": "Kherwadi_Bandra East, Mumbai - MPCB",
      "date": "2025-04-20",
      "time": "15:00:00",
      "PM2.5": 34,
      "PM10": 81,
      "NO": "NA",
      "NO2": 31,
      "NOx": "NA",
      "NH3": 2,
      "SO2": 1,
      "CO": 12,
      "Ozone": 41,
      "predominant": "PM10",
      "AQI": 81
    },
    {
      "location": "Mindspace-Malad West, Mumbai - MPCB",
      "date": "2025-04-20",
      "time": "15:00:00",
      "PM2.5": 36,
      "PM10": 45,
      "NO": "NA",
      "NO2": 13,
      "NOx": "NA",
      "NH3": 2,
      "SO2": 8,
      "CO": 15,
      "Ozone": 33,
      "predominant": "PM10",
      "AQI": 45
    },
    {
      "location": "Byculla, Mumbai - BMC",
      "date": "2025-04-20",
      "time": "15:00:00",
      "PM2.5": 26,
      "PM10": 47,
      "NO": "NA",
      "NO2": 25,
      "NOx": "NA",
      "NH3": 6,
      "SO2": 1,
      "CO": 13,
      "Ozone": 36,
      "predominant": "PM10",
      "AQI": 47
    },
    {
      "location": "Kandivali West, Mumbai - BMC",
      "date": "2025-04-20",
      "time": "15:00:00",
      "PM2.5": 18,
      "PM10": 38,
      "NO": "NA",
      "NO2": 16,
      "NOx": "NA",
      "NH3": 7,
      "SO2": 2,
      "CO": 13,
      "Ozone": 24,
      "predominant": "PM10",
      "AQI": 38
    },
    {
      "location": "Divisional Forest Office, Rairangpur - OSPCB",
      "date": "2025-04-20",
      "time": "15:00:00",
      "PM2.5": 81,
      "PM10": 79,
      "NO": "NA",
      "NO2": 17,
      "NOx": "NA",
      "NH3": 2,
      "SO2": 10,
      "CO": 13,
      "Ozone": 20,
      "predominant": "PM2.5",
      "AQI": 81
    },
    {
      "location": "Shivaji Nagar, Jhansi - UPPCB",
      "date": "2025-04-20",
      "time": "15:00:00",
      "PM2.5": 92,
      "PM10": 153,
      "NO": "NA",
      "NO2": 6,
      "NOx": "NA",
      "NH3": 4,
      "SO2": 52,
      "CO": 11,
      "Ozone": 7,
      "predominant": "PM10",
      "AQI": 153
    },
    {
      "location": "Shivaji Nagar, Rishikesh - UKPCB",
      "date": "2025-04-20",
      "time": "15:00:00",
      "PM2.5": 15,
      "PM10": 76,
      "NO": "NA",
      "NO2": 12,
      "NOx": "NA",
      "NH3": 10,
      "SO2": 4,
      "CO": 24,
      "Ozone": 44,
      "predominant": "PM10",
      "AQI": 76
    }
  ]
}