{
  "last_updated": "2026-02-05T09:39:46",
  "data": [
    {
      "location": "Kurla, Mumbai - MPCB",
      "date": "2026-02-05",
      "time": "09:00:00",
      "PM2.5": 109,
      "PM10": 123,
      "NO": "NA",
      "NO2": 7,
      "NOx": "NA",
      "NH3": 2,
      "SO2": 37,
      "CO": 24,
      "Ozone": 28,
      "predominant": "PM10",
      "AQI": 123
    },
    {
      "location": "Chhatrapati Shivaji Intl. Airport (T2), Mumbai - MPCB",
      "date": "2026-02-05",
      "time": "09:00:00",
      "PM2.5": 112,
      "PM10": 121,
      "NO": "NA",
      "NO2": 1,
      "NOx": "NA",
      "NH3": "NA",
      "SO2": 21,
      "CO": "NA",
      "Ozone": 7,
      "predominant": "PM10",
      "AQI": 121
    },
    {
      "location": "Powai, Mumbai - MPCB",
      "date": "2026-02-05",
      "time": "09:00:00",
      "PM2.5": "NA",
      "PM10": "NA",
      "NO": "NA",
      "NO2": "NA",
      "NOx": "NA",
      "NH3": "NA",
      "SO2": "NA",
      "CO": "NA",
      "Ozone": "NA",
      "predominant": "NA",
      "AQI": "NA"
    },
    {
      "location": "Vile Parle West, Mumbai - MPCB",
      "date": "2026-02-05",
      "time": "09:00:00",
      "PM2.5": 104,
      "PM10": 133,
      "NO": "NA",
      "NO2": 11,
      "NOx": "NA",
      "NH3": 6,
      "SO2": 49,
      "CO": 24,
      "Ozone": "NA",
      "predominant": "PM10",
      "AQI": 133
    },
    {
      "location": "Borivali East, Mumbai - MPCB",
      "date": "2026-02-05",
      "time": "09:00:00",
      "PM2.5": 52,
      "PM10": 94,
      "NO": "NA",
      "NO2": "NA",
      "NOx": "NA",
      "NH3": 4,
      "SO2": 16,
      "CO": 16,
      "Ozone": 18,
      "predominant": "PM10",
      "AQI": 94
    },
    {
      "location": "Colaba, Mumbai - MPCB",
      "date": "2026-02-05",
      "time": "09:00:00",
      "PM2.5": 113,
      "PM10": 117,
      "NO": "NA",
      "NO2": "NA",
      "NOx": "NA",
      "NH3": "NA",
      "SO2": "NA",
      "CO": 69,
      "Ozone": 11,
      "predominant": "PM10",
      "AQI": 117
    },
    {
      "location": "Mazgaon, Mumbai - IITM",
      "date": "2026-02-05",
      "time": "09:00:00",
      "PM2.5": 129,
      "PM10": 108,
      "NO": "NA",
      "NO2": "NA",
      "NOx": "NA",
      "NH3": "NA",
      "SO2": 16,
      "CO": 82,
      "Ozone": 10,
      "predominant": "PM2.5",
      "AQI": 129
    },
    {
      "location": "Bandra Kurla Complex, Mumbai - IITM",
      "date": "2026-02-05",
      "time": "09:00:00",
      "PM2.5": 165,
      "PM10": 145,
      "NO": "NA",
      "NO2": 87,
      "NOx": "NA",
      "NH3": 14,
      "SO2": 16,
      "CO": 60,
      "Ozone": 9,
      "predominant": "PM2.5",
      "AQI": 165
    },
    {
      "location": "Borivali East, Mumbai - IITM",
      "date": "2026-02-05",
      "time": "09:00:00",
      "PM2.5": 109,
      "PM10": 125,
      "NO": "NA",
      "NO2": "NA",
      "NOx": "NA",
      "NH3": "NA",
      "SO2": "NA",
      "CO": 53,
      "Ozone": 46,
      "predominant": "PM10",
      "AQI": 125
    },
    {
      "location": "Malad West, Mumbai - IITM",
      "date": "2026-02-05",
      "time": "09:00:00",
      "PM2.5": 109,
      "PM10": 153,
      "NO": "NA",
      "NO2": 77,
      "NOx": "NA",
      "NH3": 14,
      "SO2": 24,
      "CO": 79,
      "Ozone": 2,
      "predominant": "PM10",
      "AQI": 153
    },
    {
      "location": "Navy Nagar-Colaba, Mumbai - IITM",
      "date": "2026-02-05",
      "time": "09:00:00",
      "PM2.5": "NA",
      "PM10": 153,
      "NO": "NA",
      "NO2": 104,
      "NOx": "NA",
      "NH3": 6,
      "SO2": 24,
      "CO": 70,
      "Ozone": 15,
      "predominant": "PM10",
      "AQI": 153
    },
    {
      "location": "Chakala-Andheri East, Mumbai - IITM",
      "date": "2026-02-05",
      "time": "09:00:00",
      "PM2.5": 157,
      "PM10": 135,
      "NO": "NA",
      "NO2": 80,
      "NOx": "NA",
      "NH3": 18,
      "SO2": 8,
      "CO": 33,
      "Ozone": 6,
      "predominant": "PM2.5",
      "AQI": 157
    },
    {
      "location": "Khindipada-Bhandup West, Mumbai - IITM",
      "date": "2026-02-05",
      "time": "09:00:00",
      "PM2.5": "NA",
      "PM10": 97,
      "NO": "NA",
      "NO2": 39,
      "NOx": "NA",
      "NH3": 5,
      "SO2": 17,
      "CO": 21,
      "Ozone": 29,
      "predominant": "PM10",
      "AQI": 97
    },
    {
      "location": "Kandivali East, Mumbai - MPCB",
      "date": "2026-02-05",
      "time": "09:00:00",
      "PM2.5": 41,
      "PM10": 132,
      "NO": "NA",
      "NO2": 30,
      "NOx": "NA",
      "NH3": 3,
      "SO2": 25,
      "CO": 20,
      "Ozone": 18,
      "predominant": "PM10",
      "AQI": 132
    },
    {
      "location": "Siddharth Nagar-Worli, Mumbai - IITM",
      "date": "2026-02-05",
      "time": "09:00:00",
      "PM2.5": 127,
      "PM10": 123,
      "NO": "NA",
      "NO2": 64,
      "NOx": "NA",
      "NH3": 6,
      "SO2": "NA",
      "CO": 62,
      "Ozone": 42,
      "predominant": "PM2.5",
      "AQI": 127
    },
    {
      "location": "Bandra Kurla Complex, Mumbai - MPCB",
      "date": "2026-02-05",
      "time": "09:00:00",
      "PM2.5": 138,
      "PM10": 140,
      "NO": "NA",
      "NO2": 63,
      "NOx": "NA",
      "NH3": "NA",
      "SO2": 6,
      "CO": 11,
      "Ozone": 3,
      "predominant": "PM10",
      "AQI": 140
    },
    {
      "location": "Chembur, Mumbai - MPCB",
      "date": "2026-02-05",
      "time": "09:00:00",
      "PM2.5": 95,
      "PM10": 115,
      "NO": "NA",
      "NO2": 40,
      "NOx": "NA",
      "NH3": 13,
      "SO2": 11,
      "CO": 63,
      "Ozone": 8,
      "predominant": "PM10",
      "AQI": 115
    },
    {
      "location": "Kherwadi_Bandra East, Mumbai - MPCB",
      "date": "2026-02-05",
      "time": "09:00:00",
      "PM2.5": 49,
      "PM10": 132,
      "NO": "NA",
      "NO2": 43,
      "NOx": "NA",
      "NH3": 17,
      "SO2": "NA",
      "CO": 56,
      "Ozone": "NA",
      "predominant": "PM10",
      "AQI": 132
    },
    {
      "location": "Byculla, Mumbai - BMC",
      "date": "2026-02-05",
      "time": "09:00:00",
      "PM2.5": 143,
      "PM10": 113,
      "NO": "NA",
      "NO2": 82,
      "NOx": "NA",
      "NH3": 18,
      "SO2": 2,
      "CO": 95,
      "Ozone": "NA",
      "predominant": "PM2.5",
      "AQI": 143
    },
    {
      "location": "Shivaji Nagar, Mumbai - BMC",
      "date": "2026-02-05",
      "time": "09:00:00",
      "PM2.5": 93,
      "PM10": 123,
      "NO": "NA",
      "NO2": 16,
      "NOx": "NA",
      "NH3": 3,
      "SO2": 17,
      "CO": 36,
      "Ozone": 2,
      "predominant": "PM10",
      "AQI": 123
    }
  ]
}