{
  "last_updated": "2025-10-21T04:43:24",
  "data": [
    {
      "location": "Kurla, Mumbai - MPCB",
      "date": "2025-10-21",
      "time": "04:00:00",
      "PM2.5": 107,
      "PM10": 121,
      "NO": "NA",
      "NO2": 6,
      "NOx": "NA",
      "NH3": 2,
      "SO2": 37,
      "CO": 13,
      "Ozone": 28,
      "predominant": "PM10",
      "AQI": 121
    },
    {
      "location": "Powai, Mumbai - MPCB",
      "date": "2025-10-21",
      "time": "04:00:00",
      "PM2.5": 236,
      "PM10": 206,
      "NO": "NA",
      "NO2": 8,
      "NOx": "NA",
      "NH3": 2,
      "SO2": 28,
      "CO": 15,
      "Ozone": 9,
      "predominant": "PM2.5",
      "AQI": 236
    },
    {
      "location": "Vile Parle West, Mumbai - MPCB",
      "date": "2025-10-21",
      "time": "04:00:00",
      "PM2.5": 171,
      "PM10": 167,
      "NO": "NA",
      "NO2": 20,
      "NOx": "NA",
      "NH3": 3,
      "SO2": 39,
      "CO": 25,
      "Ozone": 19,
      "predominant": "PM2.5",
      "AQI": 171
    },
    {
      "location": "Borivali East, Mumbai - MPCB",
      "date": "2025-10-21",
      "time": "04:00:00",
      "PM2.5": 194,
      "PM10": 150,
      "NO": "NA",
      "NO2": 5,
      "NOx": "NA",
      "NH3": 2,
      "SO2": 16,
      "CO": 11,
      "Ozone": 16,
      "predominant": "PM2.5",
      "AQI": 194
    },
    {
      "location": "Worli, Mumbai - MPCB",
      "date": "2025-10-21",
      "time": "04:00:00",
      "PM2.5": 120,
      "PM10": 118,
      "NO": "NA",
      "NO2": 8,
      "NOx": "NA",
      "NH3": 1,
      "SO2": 20,
      "CO": 8,
      "Ozone": 20,
      "predominant": "PM2.5",
      "AQI": 120
    },
    {
      "location": "Colaba, Mumbai - MPCB",
      "date": "2025-10-21",
      "time": "04:00:00",
      "PM2.5": 149,
      "PM10": 129,
      "NO": "NA",
      "NO2": 28,
      "NOx": "NA",
      "NH3": 3,
      "SO2": "NA",
      "CO": 28,
      "Ozone": 11,
      "predominant": "PM2.5",
      "AQI": 149
    },
    {
      "location": "Mazgaon, Mumbai - IITM",
      "date": "2025-10-21",
      "time": "04:00:00",
      "PM2.5": 306,
      "PM10": 191,
      "NO": "NA",
      "NO2": 74,
      "NOx": "NA",
      "NH3": 16,
      "SO2": 10,
      "CO": 86,
      "Ozone": 34,
      "predominant": "PM2.5",
      "AQI": 306
    },
    {
      "location": "Bandra Kurla Complex, Mumbai - IITM",
      "date": "2025-10-21",
      "time": "04:00:00",
      "PM2.5": 372,
      "PM10": 295,
      "NO": "NA",
      "NO2": 54,
      "NOx": "NA",
      "NH3": 36,
      "SO2": 2,
      "CO": 42,
      "Ozone": 6,
      "predominant": "PM2.5",
      "AQI": 372
    },
    {
      "location": "Borivali East, Mumbai - IITM",
      "date": "2025-10-21",
      "time": "04:00:00",
      "PM2.5": 265,
      "PM10": 201,
      "NO": "NA",
      "NO2": 64,
      "NOx": "NA",
      "NH3": 7,
      "SO2": "NA",
      "CO": 71,
      "Ozone": 47,
      "predominant": "PM2.5",
      "AQI": 265
    },
    {
      "location": "Malad West, Mumbai - IITM",
      "date": "2025-10-21",
      "time": "04:00:00",
      "PM2.5": 270,
      "PM10": 257,
      "NO": "NA",
      "NO2": 64,
      "NOx": "NA",
      "NH3": 6,
      "SO2": 6,
      "CO": 37,
      "Ozone": 39,
      "predominant": "PM2.5",
      "AQI": 270
    },
    {
      "location": "Navy Nagar-Colaba, Mumbai - IITM",
      "date": "2025-10-21",
      "time": "04:00:00",
      "PM2.5": 335,
      "PM10": 224,
      "NO": "NA",
      "NO2": 137,
      "NOx": "NA",
      "NH3": 7,
      "SO2": 13,
      "CO": 31,
      "Ozone": 41,
      "predominant": "PM2.5",
      "AQI": 335
    },
    {
      "location": "Chakala-Andheri East, Mumbai - IITM",
      "date": "2025-10-21",
      "time": "04:00:00",
      "PM2.5": 277,
      "PM10": 185,
      "NO": "NA",
      "NO2": 64,
      "NOx": "NA",
      "NH3": 12,
      "SO2": 5,
      "CO": 41,
      "Ozone": 24,
      "predominant": "PM2.5",
      "AQI": 277
    },
    {
      "location": "Khindipada-Bhandup West, Mumbai - IITM",
      "date": "2025-10-21",
      "time": "04:00:00",
      "PM2.5": "NA",
      "PM10": 138,
      "NO": "NA",
      "NO2": 16,
      "NOx": "NA",
      "NH3": 12,
      "SO2": 12,
      "CO": 44,
      "Ozone": 46,
      "predominant": "PM10",
      "AQI": 138
    },
    {
      "location": "Kandivali East, Mumbai - MPCB",
      "date": "2025-10-21",
      "time": "04:00:00",
      "PM2.5": 144,
      "PM10": 129,
      "NO": "NA",
      "NO2": 9,
      "NOx": "NA",
      "NH3": 1,
      "SO2": "NA",
      "CO": 25,
      "Ozone": "NA",
      "predominant": "PM2.5",
      "AQI": 144
    },
    {
      "location": "Siddharth Nagar-Worli, Mumbai - IITM",
      "date": "2025-10-21",
      "time": "04:00:00",
      "PM2.5": 267,
      "PM10": 165,
      "NO": "NA",
      "NO2": 60,
      "NOx": "NA",
      "NH3": 5,
      "SO2": "NA",
      "CO": 78,
      "Ozone": 26,
      "predominant": "PM2.5",
      "AQI": 267
    },
    {
      "location": "Bandra Kurla Complex, Mumbai - MPCB",
      "date": "2025-10-21",
      "time": "04:00:00",
      "PM2.5": 251,
      "PM10": 187,
      "NO": "NA",
      "NO2": 38,
      "NOx": "NA",
      "NH3": 8,
      "SO2": 5,
      "CO": 34,
      "Ozone": 19,
      "predominant": "PM2.5",
      "AQI": 251
    },
    {
      "location": "Chembur, Mumbai - MPCB",
      "date": "2025-10-21",
      "time": "04:00:00",
      "PM2.5": 201,
      "PM10": 145,
      "NO": "NA",
      "NO2": 32,
      "NOx": "NA",
      "NH3": 4,
      "SO2": 8,
      "CO": 59,
      "Ozone": 22,
      "predominant": "PM2.5",
      "AQI": 201
    },
    {
      "location": "Kherwadi_Bandra East, Mumbai - MPCB",
      "date": "2025-10-21",
      "time": "04:00:00",
      "PM2.5": 235,
      "PM10": 193,
      "NO": "NA",
      "NO2": 35,
      "NOx": "NA",
      "NH3": 9,
      "SO2": 5,
      "CO": 51,
      "Ozone": 10,
      "predominant": "PM2.5",
      "AQI": 235
    },
    {
      "location": "Byculla, Mumbai - BMC",
      "date": "2025-10-21",
      "time": "04:00:00",
      "PM2.5": 258,
      "PM10": 144,
      "NO": "NA",
      "NO2": 47,
      "NOx": "NA",
      "NH3": 9,
      "SO2": 8,
      "CO": 19,
      "Ozone": 32,
      "predominant": "PM2.5",
      "AQI": 258
    },
    {
      "location": "Shivaji Nagar, Mumbai - BMC",
      "date": "2025-10-21",
      "time": "04:00:00",
      "PM2.5": "NA",
      "PM10": 134,
      "NO": "NA",
      "NO2": 32,
      "NOx": "NA",
      "NH3": 3,
      "SO2": 11,
      "CO": 48,
      "Ozone": 25,
      "predominant": "PM10",
      "AQI": 134
    }
  ]
}